CHANGES.txt
MANIFEST.in
README.rst
setup.py
nose_docstring_modifier/__init__.py
nose_docstring_modifier/nose_docstring_modifier.py
nose_docstring_modifier.egg-info/PKG-INFO
nose_docstring_modifier.egg-info/SOURCES.txt
nose_docstring_modifier.egg-info/dependency_links.txt
nose_docstring_modifier.egg-info/entry_points.txt
nose_docstring_modifier.egg-info/not-zip-safe
nose_docstring_modifier.egg-info/requires.txt
nose_docstring_modifier.egg-info/top_level.txt