Metadata-Version: 1.1
Name: nose-docstring-modifier
Version: 0.0.6
Summary: Enables you to modify docstring of tests based on their attributes
Home-page: https://github.com/taykey/nose-docstring-modifier
Author: Maroun Maroun
Author-email: maroun@taykey.com
License: UNKNOWN
Keywords: nosetest docstring
Platform: UNKNOWN
Classifier: Development Status :: 4 - Beta
Classifier: Intended Audience :: Developers
Classifier: Operating System :: OS Independent
Classifier: Programming Language :: Python
Classifier: Topic :: Software Development :: Testing
Classifier: License :: OSI Approved :: Apache Software License
